<?xml version="1.0" encoding="ISO-8859-1"?>
<!DOCTYPE struts-config PUBLIC "-//Apache Software Foundation//DTD Struts Configuration 1.1//EN" "http://jakarta.apache.org/struts/dtds/struts-config_1_1.dtd">
<struts-config>

	<!-- Data Sources -->
	<data-sources></data-sources>

	<!-- Form Beans -->
	<form-beans></form-beans>

	<!-- Global Exceptions -->
	<global-exceptions></global-exceptions>

	<!-- Global Forwards -->
	<global-forwards>
      
    </global-forwards>
    
    <action-mappings>
        <action path="/afficherLabel" type="org.kramaframework.demo.TestAction">
        	<forward name="success" path="/sal_test.jsp" />
        </action>    
    	
	</action-mappings>

	<!-- Message Resources -->
	<message-resources parameter="ApplicationResources" />

</struts-config>
